layercode_gym/__init__.py
layercode_gym/agents/__init__.py
layercode_gym/agents/judge.py
layercode_gym/agents/prompts/criteria_judge.txt
layercode_gym/api_agents_cli.py
layercode_gym/api_agents_utils.py
layercode_gym/callbacks.py
layercode_gym/cli.py
layercode_gym/client.py
layercode_gym/config.py
layercode_gym/logging_utils.py
layercode_gym/models/conversation.py
layercode_gym/models/events.py
layercode_gym/py.typed
layercode_gym/runner.py
layercode_gym/simulator/__init__.py
layercode_gym/simulator/agent.py
layercode_gym/simulator/base.py
layercode_gym/simulator/basic_agent.py
layercode_gym/simulator/data_processor.py
layercode_gym/simulator/prompts/basic_agent.txt
layercode_gym/simulator/protocols.py
layercode_gym/simulator/tts.py
layercode_gym/storage.py
layercode_gym/tunnel.py
layercode_gym/turn_dispatch/__init__.py
layercode_gym/turn_dispatch/prompts/smart_turn_classifier.txt
layercode_gym/turn_dispatch/protocols.py
layercode_gym/turn_dispatch/smart_turn.py
layercode_gym/utils/audio.py
layercode_gym-0.7.0.dist-info/licenses/LICENSE
layercode_gym-0.7.0.dist-info/WHEEL
layercode_gym-0.7.0.dist-info/entry_points.txt
layercode_gym-0.7.0.dist-info/METADATA
layercode_gym-0.7.0.dist-info/RECORD
