Metadata-Version: 2.4
Name: layercode-gym
Version: 0.7.0
Summary: Utilities for simulating LayerCode voice agent conversations
Author: Jan Siml
Author-email: Jan Siml <49557684+svilupp@users.noreply.github.com>
License-Expression: MIT
License-File: LICENSE
Requires-Dist: logfire>=4.14.2
Requires-Dist: openai>=2.6.1
Requires-Dist: pydantic-ai>=1.9.1
Requires-Dist: pydantic>=2.10.0
Requires-Dist: pydub>=0.25.1
Requires-Dist: python-dotenv>=1.2.1
Requires-Dist: textprompts>=1.1.0
Requires-Dist: tqdm>=4.67.1
Requires-Dist: httpx>=0.27.2
Requires-Dist: websockets>=12.0
Requires-Dist: audioop-lts ; python_full_version >= '3.13'
Requires-Python: >=3.11
Project-URL: Bug Tracker, https://github.com/svilupp/layercode-gym/issues
Project-URL: Documentation, https://svilupp.github.io/layercode-gym
Project-URL: Homepage, https://github.com/svilupp/layercode-gym
